{
	"contracts": {
		"FlowDEX": {
			"source": "./cadence/contracts/FlowDEX.cdc",
			"aliases": {
				"emulator": "0xf8d6e0586b0a20c7",
				"testnet": "0x91493e72be60e71e",
				"mainnet": "0x0000000000000000"
			}
		},
		"TestToken": {
			"source": "./cadence/contracts/TestToken.cdc",
			"aliases": {
				"emulator": "0xf8d6e0586b0a20c7",
				"testnet": "0x91493e72be60e71e",
				"mainnet": "0x0000000000000000"
			}
		},
		"TestToken2": {
			"source": "./cadence/contracts/TestToken2.cdc",
			"aliases": {
				"emulator": "0xf8d6e0586b0a20c7",
				"testnet": "0x665d58f94c100bdb",
				"mainnet": "0x0000000000000000"
			}
		},
		"FungibleToken": {
			"source": "https://raw.githubusercontent.com/onflow/flow-ft/master/contracts/FungibleToken.cdc",
			"aliases": {
				"emulator": "0xee82856bf20e2aa6",
				"testnet": "0x9a0766d93b6608b7",
				"mainnet": "0xf233dcee88fe0abe"
			}
		}
	},
	"networks": {
		"emulator": "127.0.0.1:3569",
		"testnet": "https://rest-testnet.onflow.org",
		"mainnet": "https://rest-mainnet.onflow.org"
	},
	"accounts": {
		"p2": {
			"address": "0x91493e72be60e71e",
			"key": {
				"type": "hex",
				"index": 0,
				"signatureAlgorithm": "ECDSA_P256",
				"hashAlgorithm": "SHA3_256"
			}
		},
		"pandit": {
			"address": "0x665d58f94c100bdb",
			"key": {
				"type": "hex",
				"index": 0,
				"signatureAlgorithm": "ECDSA_P256",
				"hashAlgorithm": "SHA3_256"
			}
		}
	},
	"deployments": {
		"testnet": {
			"p2": [
				"FlowDEX",
				"TestToken"
			],
			"pandit": [
				"TestToken2"
			]
		}
	}
}